LICENSE
MANIFEST.in
README.rst
setup.py
chembl_assay_network/__init__.py
chembl_assay_network/matrix.py
chembl_assay_network/models.py
chembl_assay_network/tests.py
chembl_assay_network/urls.py
chembl_assay_network/views.py
chembl_assay_network.egg-info/PKG-INFO
chembl_assay_network.egg-info/SOURCES.txt
chembl_assay_network.egg-info/dependency_links.txt
chembl_assay_network.egg-info/not-zip-safe
chembl_assay_network.egg-info/requires.txt
chembl_assay_network.egg-info/top_level.txt
chembl_assay_network/static/css/cooccurance.css
chembl_assay_network/static/css/d3tip.css
chembl_assay_network/static/css/jquery.dataTables.css
chembl_assay_network/static/img/back_disabled.png
chembl_assay_network/static/img/back_enabled.png
chembl_assay_network/static/img/back_enabled_hover.png
chembl_assay_network/static/img/chembl.png
chembl_assay_network/static/img/forward_disabled.png
chembl_assay_network/static/img/forward_enabled.png
chembl_assay_network/static/img/forward_enabled_hover.png
chembl_assay_network/static/img/sort_asc.png
chembl_assay_network/static/img/sort_asc_disabled.png
chembl_assay_network/static/img/sort_both.png
chembl_assay_network/static/img/sort_desc.png
chembl_assay_network/static/img/sort_desc_disabled.png
chembl_assay_network/static/js/color.min.js
chembl_assay_network/static/js/cooccurance.js
chembl_assay_network/static/js/d3.min.js
chembl_assay_network/static/js/d3tip.js
chembl_assay_network/static/js/jquery-1.8.3.js
chembl_assay_network/static/js/jquery.dataTables.min.js
chembl_assay_network/static/js/jquery.js
chembl_assay_network/static/js/spin.min.js
chembl_assay_network/templates/cooccurance.html