Metadata-Version: 1.1
Name: chembl-assay-network
Version: 0.6.1
Summary: Python package generating compound co-occurance matrix for all assays from given document
Home-page: https://www.ebi.ac.uk/chembldb/index.php/ws
Author: Michal Nowotka
Author-email: mnowotka@ebi.ac.uk
License: CC BY-SA 3.0
Platform: UNKNOWN
Classifier: Development Status :: 2 - Pre-Alpha
Classifier: Environment :: Web Environment
Classifier: Framework :: Django
Classifier: Intended Audience :: Developers
Classifier: License :: OSI Approved :: Apache Software License
Classifier: Operating System :: POSIX :: Linux
Classifier: Programming Language :: Python :: 2.7
Classifier: Topic :: Scientific/Engineering :: Chemistry
